[
  {
    "name": "Makin Ahmed",
    "img": "https://i.ibb.co/ncW4jKY/president.png",
    "id": "115",
    "position": "President"
  },
  {
    "name": "Eusuf Ahmed",
    "img": "https://i.ibb.co/097dKg5/vp1.png",
    "id": "177715",
    "position": "Vice-President"
  },
  {
    "name": "Anik Sarkar",
    "img": "https://i.ibb.co/Kj5krC9/vp2.png",
    "id": "1150135",
    "position": "Vice-President"
  },
  {
    "name": "Ms. Bithi",
    "img": "https://i.ibb.co/GWzTjRn/gs.png",
    "id": "043",
    "position": "General Secretary"
  },
  {
    "name": "Biplop Gazi",
    "img": "https://i.ibb.co/cc7Mb7P/ags1.png",
    "id": "11533",
    "position": "Assistant General Secretary"
  },
  {
    "name": "Md. Rakib",
    "img": "https://i.ibb.co/ypVSXy0/ags2.png",
    "id": "115",
    "position": "Assistant General Secretary"
  },
  {
    "name": "Meherun Nesa",
    "img": "https://i.ibb.co/YjTZ72K/ags4.png",
    "id": "1155",
    "position": "Assistant General Secretary"
  },
  {
    "name": "Ahasan Jubaer",
    "img": "https://i.ibb.co/sbVQfwP/ags3.png",
    "id": "11005",
    "position": "Assistant General Secretary"
  },
  {
    "name": "Monayem Hossain",
    "img": "https://i.ibb.co/P4nffrL/aps6.png",
    "id": "012",
    "position": "Assistant General Secretary"
  },
  {
    "name": "Habibus Sharif",
    "img": "https://i.ibb.co/sysnYvz/ps.png",
    "id": "1124325",
    "position": "Press Secretary"
  },
  {
    "name": "Izharul Saikat",
    "img": "https://i.ibb.co/DfZYvz7/aps1.png",
    "id": "115",
    "position": "Assistant Press Secretary"
  },
  {
    "name": "Sharmin Sumi",
    "img": "https://i.ibb.co/1JcHSc8/aps3.png",
    "id": "051",
    "position": "Assistant Press Secretary"
  },
  {
    "name": "Macnalious Sunny",
    "img": "https://i.ibb.co/R7NJgg3/aps2.png",
    "id": "01333",
    "position": "Assistant Press Secretary"
  },
  {
    "name": "Bayezid Ahmed",
    "img": "https://i.ibb.co/mDyrZGr/aps4.png",
    "id": "098",
    "position": "Assistant Press Secretary"
  },
  {
    "name": "Sumaiya Afrin Eva",
    "img": "https://i.ibb.co/7VSd59S/aps5.png",
    "id": "004",
    "position": "Assistant Press Secretary"
  },
  {
    "name": "Emran Masud",
    "img": "https://i.ibb.co/HCxWZGb/treasurer.png",
    "id": "1085",
    "position": "Treasurer"
  },
  {
    "name": "Pulak Bala",
    "img": "https://i.ibb.co/2cSHnJd/designer.png",
    "id": "1082",
    "position": "Creative Designer"
  }
]